benchmarkthing/__init__.py
benchmarkthing-0.0.1.dist-info/METADATA
benchmarkthing-0.0.1.dist-info/WHEEL
benchmarkthing-0.0.1.dist-info/top_level.txt
benchmarkthing-0.0.1.dist-info/RECORD
