Metadata-Version: 2.1
Name: benchmarkthing
Version: 0.0.1
Summary: Evals as an API - The easiest way to evaluate and benchmark AI models and systems
Author-email: "Benchmarkthing Inc." <hello@benchmarkthing.com>
License: MIT
Project-URL: Homepage, https://benchmarkthing.com
Project-URL: Repository, https://github.com/benchmarkthing/benchmarkthing-python
Project-URL: Bug Tracker, https://github.com/benchmarkthing/benchmarkthing-python/issues
Keywords: ai,ml,evaluation,benchmark,evals,testing
Classifier: Development Status :: 1 - Planning
Classifier: Intended Audience :: Developers
Classifier: Topic :: Software Development :: Libraries :: Python Modules
Classifier: Topic :: Scientific/Engineering :: Artificial Intelligence
Classifier: License :: OSI Approved :: MIT License
Classifier: Programming Language :: Python :: 3
Classifier: Programming Language :: Python :: 3.8
Classifier: Programming Language :: Python :: 3.9
Classifier: Programming Language :: Python :: 3.10
Classifier: Programming Language :: Python :: 3.11
Classifier: Operating System :: OS Independent
Requires-Python: >=3.8
